README.md
license
setup.cfg
setup.py
src/Radi/__init__.py
src/Radi/lightening.py
src/RadiKali.egg-info/PKG-INFO
src/RadiKali.egg-info/SOURCES.txt
src/RadiKali.egg-info/dependency_links.txt
src/RadiKali.egg-info/top_level.txt