Metadata-Version: 2.1
Name: RadiKali
Version: 1.0.0
Summary: does nothing
Home-page: UNKNOWN
Author: someone
License: UNKNOWN
Platform: UNKNOWN
License-File: license
